bloom_client/__init__.py
bloom_client/client.py
bloom_client-1.0.1.dist-info/METADATA
bloom_client-1.0.1.dist-info/WHEEL
bloom_client-1.0.1.dist-info/top_level.txt
bloom_client-1.0.1.dist-info/RECORD
